odoo/addons/web_notify_channel_message/README.rst
odoo/addons/web_notify_channel_message/__init__.py
odoo/addons/web_notify_channel_message/__manifest__.py
odoo/addons/web_notify_channel_message/i18n/es.po
odoo/addons/web_notify_channel_message/i18n/fr.po
odoo/addons/web_notify_channel_message/i18n/it.po
odoo/addons/web_notify_channel_message/i18n/web_notify_channel_message.pot
odoo/addons/web_notify_channel_message/models/__init__.py
odoo/addons/web_notify_channel_message/models/discuss_channel.py
odoo/addons/web_notify_channel_message/models/res_users.py
odoo/addons/web_notify_channel_message/readme/CONTRIBUTORS.md
odoo/addons/web_notify_channel_message/readme/DESCRIPTION.md
odoo/addons/web_notify_channel_message/static/description/icon.png
odoo/addons/web_notify_channel_message/static/description/index.html
odoo/addons/web_notify_channel_message/tests/__init__.py
odoo/addons/web_notify_channel_message/tests/test_notify_channel_message.py
odoo_addon_web_notify_channel_message-18.0.1.0.1.dist-info/METADATA
odoo_addon_web_notify_channel_message-18.0.1.0.1.dist-info/WHEEL
odoo_addon_web_notify_channel_message-18.0.1.0.1.dist-info/top_level.txt
odoo_addon_web_notify_channel_message-18.0.1.0.1.dist-info/RECORD
