Metadata-Version: 2.1
Name: odoo-addon-web_notify_channel_message
Version: 18.0.1.0.1
Requires-Python: >=3.10
Requires-Dist: odoo-addon-web_notify==18.0.*
Requires-Dist: odoo==18.0.*
Summary: Send an instant notification to channel users when a new message is posted
Home-page: https://github.com/OCA/web
License: AGPL-3
Author: ForgeFlow, Odoo Community Association (OCA)
Author-email: support@odoo-community.org
Classifier: Programming Language :: Python
Classifier: Framework :: Odoo
Classifier: Framework :: Odoo :: 18.0
Classifier: License :: OSI Approved :: GNU Affero General Public License v3
Classifier: Development Status :: 3 - Alpha
